{"stat.chestOpened":4,"stat.walkOneCm":67152,"achievement.openInventory":5,"stat.leaveGame":4,"stat.damageTaken":566,"stat.craftItem.minecraft.crafting_table":1,"stat.flyOneCm":27045,"stat.deaths":1,"stat.jump":137,"stat.swimOneCm":207,"stat.playOneMinute":13812,"stat.craftItem.minecraft.wooden_shovel":1,"stat.climbOneCm":73,"stat.timeSinceDeath":5743,"stat.sprintOneCm":9690,"stat.mineBlock.minecraft.dirt":1,"stat.useItem.minecraft.crafting_table":1,"achievement.exploreAllBiomes":{"value":0,"progress":["DesertHills","River","Desert","Taiga","Savanna","Hell"]},"stat.mineBlock.minecraft.tallgrass":2,"stat.craftItem.minecraft.stick":4,"stat.craftingTableInteraction":2}