{"stat.chestOpened":151,"stat.craftItem.minecraft.cooked_rabbit":1,"stat.useItem.minecraft.fish":3,"stat.useItem.minecraft.stone":1,"stat.leaveGame":11,"stat.mineBlock.minecraft.cobblestone":16,"stat.useItem.minecraft.glass_bottle":3,"stat.killEntity.Slime":4,"stat.mineBlock.minecraft.slime":1,"stat.useItem.minecraft.chicken":3,"stat.useItem.minecraft.diamond_sword":32,"stat.jump":1414,"stat.swimOneCm":8727,"stat.climbOneCm":34396,"stat.fallOneCm":538,"stat.crouchOneCm":6183,"stat.craftItem.minecraft.iron_ingot":54,"stat.useItem.minecraft.dirt":60,"stat.craftItem.minecraft.iron_helmet":1,"stat.craftItem.minecraft.fermented_spider_eye":1,"achievement.exploreAllBiomes":{"value":0,"progress":["Sunflower Plains","ForestHills","Roofed Forest","Plains","TaigaHills","Beach","DesertHills","Stone Beach","River","Forest","Taiga","Desert","Extreme Hills","Deep Ocean","Hell"]},"stat.craftingTableInteraction":13,"stat.craftItem.minecraft.iron_boots":1,"stat.brewingstandInteraction":7,"stat.damageTaken":351,"stat.junkFished":1,"stat.mineBlock.minecraft.melon_block":63,"stat.mineBlock.minecraft.torch":4,"stat.useItem.minecraft.reeds":12,"stat.mineBlock.minecraft.spruce_fence":2,"stat.useItem.minecraft.slime":1,"stat.craftItem.minecraft.stone_sword":1,"stat.flyOneCm":159747,"stat.craftItem.minecraft.glass_bottle":3,"stat.mineBlock.minecraft.gravel":18,"stat.craftItem.minecraft.iron_leggings":1,"stat.useItem.minecraft.stone_sword":140,"stat.craftItem.minecraft.cooked_fish":5,"stat.damageDealt":46135,"stat.craftItem.minecraft.glass":39,"stat.mineBlock.minecraft.iron_ore":11,"stat.timeSinceDeath":36680,"stat.hopperInspected":35,"stat.killEntity.Cow":3,"stat.mineBlock.minecraft.dirt":62,"stat.useItem.minecraft.iron_pickaxe":943,"stat.craftItem.minecraft.stone_slab":6,"stat.walkOneCm":1011432,"stat.useItem.minecraft.torch":9,"stat.treasureFished":3,"stat.useItem.minecraft.cobblestone":22,"stat.furnaceInteraction":35,"stat.mineBlock.minecraft.coal_ore":44,"stat.useItem.minecraft.armor_stand":3,"stat.craftItem.minecraft.gold_ingot":1,"stat.craftItem.minecraft.iron_chestplate":1,"stat.sprintOneCm":217732,"stat.craftItem.minecraft.brewing_stand":1,"stat.craftItem.minecraft.stick":8,"achievement.openInventory":250,"stat.mineBlock.minecraft.stonebrick":2,"stat.useItem.minecraft.iron_sword":221,"stat.craftItem.minecraft.stone":3,"stat.killEntity.Chicken":3,"stat.craftItem.minecraft.armor_stand":1,"stat.useItem.minecraft.wheat_seeds":95,"stat.useItem.minecraft.diamond_pickaxe":11,"stat.mobKills":216,"stat.useItem.minecraft.stonebrick":2,"stat.useItem.minecraft.beef":5,"stat.deaths":1,"stat.drop":277,"stat.playOneMinute":342637,"stat.mineBlock.minecraft.redstone_ore":18,"stat.killEntity.Zombie":206,"stat.useItem.minecraft.brewing_stand":1,"stat.breakItem.minecraft.stone_sword":1,"stat.mineBlock.minecraft.stone":838,"stat.mineBlock.minecraft.tallgrass":4,"stat.fishCaught":55,"stat.craftItem.minecraft.cooked_mutton":4,"stat.diveOneCm":7260,"stat.useItem.minecraft.fishing_rod":160}